quanti_gin/__init__.py
quanti_gin/__main__.py
quanti_gin/data_generator.py
quanti_gin/environment.yml
quanti_gin/examples/__init__.py
quanti_gin/examples/custom_method.py
quanti_gin/shared.py
quanti_gin-2.5.0.dist-info/LICENSE
quanti_gin-2.5.0.dist-info/METADATA
quanti_gin-2.5.0.dist-info/WHEEL
quanti_gin-2.5.0.dist-info/RECORD
