Metadata-Version: 2.3
Name: quanti-gin
Version: 2.5.0
Summary: A customizable data generator for quantum simulation
License: MIT
Author: Korbinian Stein
Author-email: kstein@inforbi.de
Requires-Python: >=3.10
Classifier: License :: OSI Approved :: MIT License
Classifier: Programming Language :: Python :: 3
Classifier: Programming Language :: Python :: 3.10
Classifier: Programming Language :: Python :: 3.11
Classifier: Programming Language :: Python :: 3.12
Classifier: Programming Language :: Python :: 3.13
Requires-Dist: numpy
Requires-Dist: pandas (>=2.2.2,<3.0.0)
Requires-Dist: tequila-basic (>=1.9.8,<2.0.0)
Project-URL: Repository, https://github.com/nylser/quanti-gin
